pytrends/__init__.py
pytrends/dailydata.py
pytrends/exceptions.py
pytrends/request.py
pytrends-4.9.2.dist-info/LICENSE
pytrends-4.9.2.dist-info/METADATA
pytrends-4.9.2.dist-info/WHEEL
pytrends-4.9.2.dist-info/top_level.txt
pytrends-4.9.2.dist-info/RECORD
