Metadata-Version: 2.1
Name: pytrends
Version: 4.9.2
Summary: Pseudo API for Google Trends
Author: John Hogue, Burton DeWilde
Author-email: dreyco676@gmail.com
License: Apache 2.0
Project-URL: homepage, https://github.com/dreyco676/pytrends
Keywords: google trends api search
Classifier: Development Status :: 4 - Beta
Classifier: Intended Audience :: Developers
Classifier: Programming Language :: Python :: 3.7
Classifier: Programming Language :: Python :: 3.8
Classifier: Programming Language :: Python :: 3.9
Classifier: Programming Language :: Python :: 3.10
Classifier: Programming Language :: Python :: 3.11
Classifier: License :: OSI Approved :: Apache Software License
Requires-Python: >=3.7
License-File: LICENSE
